sync_cwbq/__init__.py
sync_cwbq/database.py
sync_cwbq/sync_cwbq.py
sync_cwbq/tasks.py
sync_cwbq-0.1.3.dist-info/licenses/LICENSE
sync_cwbq-0.1.3.dist-info/METADATA
sync_cwbq-0.1.3.dist-info/WHEEL
sync_cwbq-0.1.3.dist-info/top_level.txt
sync_cwbq-0.1.3.dist-info/RECORD
