Metadata-Version: 2.4
Name: sync_cwbq
Version: 0.1.3
Summary: 同步mongodb数据到数仓
Author-email: cwbq <940040346@qq.com>
License-Expression: MIT
Project-URL: Homepage, https://gitee.com/little-tomato/chagee-sync
Project-URL: Issues, https://gitee.com/little-tomato/chagee-sync/issues
Classifier: Programming Language :: Python :: 3
Classifier: Operating System :: OS Independent
Requires-Python: >=3.9
License-File: LICENSE
Requires-Dist: celery==5.5.3
Requires-Dist: loguru==0.7.3
Requires-Dist: pymongo==4.15.3
Requires-Dist: pyodps==0.12.5
Requires-Dist: redis==7.0.1
Requires-Dist: python-dotenv==1.2.1
Requires-Dist: dnspython==2.8.0
Dynamic: license-file
